LICENSE
arrayclasses/__init__.py
arrayclasses/wrapper.py
arrayclasses-0.1.4.dist-info/LICENSE
arrayclasses-0.1.4.dist-info/WHEEL
arrayclasses-0.1.4.dist-info/METADATA
arrayclasses-0.1.4.dist-info/RECORD
