Metadata-Version: 2.1
Name: arrayclasses
Version: 0.1.4
Summary: Analogue to dataclass that uses a numpy-backed array to store values.
Home-page: https://github.com/Ivorforce/python-arrayclass
License: MIT
Keywords: numpy,dataclass
Author: Lukas Tenbrink
Author-email: lukas.tenbrink@gmail.com
Requires-Python: >=3.9,<4.0
Classifier: License :: OSI Approved :: MIT License
Classifier: Programming Language :: Python :: 3
Classifier: Programming Language :: Python :: 3.9
Requires-Dist: numpy (>=1.24.3,<2.0.0)
Project-URL: Repository, https://github.com/Ivorforce/python-arrayclass
